Workbook

Sheet Teacher's Sheet
C2: Teacher's Result Sheet for HSC Exam 2025-26
B5: Roll NO. | C5: Name | D5: Physics | E5: Chemistry | F5: Maths | G5: Biology | H5: English | I5: Computer | J5: Min | K5: Max | L5: Total | M5: Average | N5: Grade | O5: Result
B6: HSC01 | C6: Krish | D6: 99 | E6: 97 | F6: 100 | G6: 80 | H6: 86 | I6: 100 | J6: =MIN(D6:I6) -> 80 | K6: =MAX(D6:I6) -> 100 | L6: =SUM(D6:I6) -> 562 | M6: =AVERAGE(D6:I6) -> 93.666667 | N6: =IF(M6>90,"A",IF(M6>80,"B",IF(M6>70,"C",IF(M6>=33,"D","E")))) -> A | O6: =IF(M6>=33, "Pass", "Fail") -> Pass
B7: HSC02 | C7: Deven | D7: 70 | E7: 71 | F7: 60 | G7: 98 | H7: 86 | I7: 80 | J7: =MIN(D7:I7) -> 60 | K7: =MAX(D7:I7) -> 98 | L7: =SUM(D7:I7) -> 465 | M7: =AVERAGE(D7:I7) -> 77.5 | N7: =IF(M7>90,"A",IF(M7>80,"B",IF(M7>70,"C",IF(M7>=33,"D","E")))) -> C | O7: =IF(M7>=33, "Pass", "Fail") -> Pass
B8: HSC03 | C8: Shivam | D8: 34 | E8: 85 | F8: 60 | G8: 78 | H8: 83 | I8: 78 | J8: =MIN(D8:I8) -> 34 | K8: =MAX(D8:I8) -> 85 | L8: =SUM(D8:I8) -> 418 | M8: =AVERAGE(D8:I8) -> 69.666667 | N8: =IF(M8>90,"A",IF(M8>80,"B",IF(M8>70,"C",IF(M8>=33,"D","E")))) -> D | O8: =IF(M8>=33, "Pass", "Fail") -> Pass
B9: HSC04 | C9: Dhirendra | D9: 56 | E9: 34 | F9: 47 | G9: 77 | H9: 98 | I9: 88 | J9: =MIN(D9:I9) -> 34 | K9: =MAX(D9:I9) -> 98 | L9: =SUM(D9:I9) -> 400 | M9: =AVERAGE(D9:I9) -> 66.666667 | N9: =IF(M9>90,"A",IF(M9>80,"B",IF(M9>70,"C",IF(M9>=33,"D","E")))) -> D | O9: =IF(M9>=33, "Pass", "Fail") -> Pass
B10: HSC05 | C10: Sahil | D10: 28 | E10: 95 | F10: 30 | G10: 73 | H10: 62 | I10: 39 | J10: =MIN(D10:I10) -> 28 | K10: =MAX(D10:I10) -> 95 | L10: =SUM(D10:I10) -> 327 | M10: =AVERAGE(D10:I10) -> 54.5 | N10: =IF(M10>90,"A",IF(M10>80,"B",IF(M10>70,"C",IF(M10>=33,"D","E")))) -> D | O10: =IF(M10>=33, "Pass", "Fail") -> Pass
B11: HSC06 | C11: Kartik | D11: 86 | E11: 38 | F11: 90 | G11: 67 | H11: 75 | I11: 40 | J11: =MIN(D11:I11) -> 38 | K11: =MAX(D11:I11) -> 90 | L11: =SUM(D11:I11) -> 396 | M11: =AVERAGE(D11:I11) -> 66 | N11: =IF(M11>90,"A",IF(M11>80,"B",IF(M11>70,"C",IF(M11>=33,"D","E")))) -> D | O11: =IF(M11>=33, "Pass", "Fail") -> Pass
B12: HSC07 | C12: Satyam | D12: 97 | E12: 90 | F12: 78 | G12: 33 | H12: 75 | I12: 94 | J12: =MIN(D12:I12) -> 33 | K12: =MAX(D12:I12) -> 97 | L12: =SUM(D12:I12) -> 467 | M12: =AVERAGE(D12:I12) -> 77.833333 | N12: =IF(M12>90,"A",IF(M12>80,"B",IF(M12>70,"C",IF(M12>=33,"D","E")))) -> C | O12: =IF(M12>=33, "Pass", "Fail") -> Pass
B13: HSC08 | C13: Atharv | D13: 35 | E13: 46 | F13: 97 | G13: 70 | H13: 52 | I13: 98 | J13: =MIN(D13:I13) -> 35 | K13: =MAX(D13:I13) -> 98 | L13: =SUM(D13:I13) -> 398 | M13: =AVERAGE(D13:I13) -> 66.333333 | N13: =IF(M13>90,"A",IF(M13>80,"B",IF(M13>70,"C",IF(M13>=33,"D","E")))) -> D | O13: =IF(M13>=33, "Pass", "Fail") -> Pass
B14: HSC09 | C14: Jay | D14: 71 | E14: 31 | F14: 96 | G14: 44 | H14: 59 | I14: 45 | J14: =MIN(D14:I14) -> 31 | K14: =MAX(D14:I14) -> 96 | L14: =SUM(D14:I14) -> 346 | M14: =AVERAGE(D14:I14) -> 57.666667 | N14: =IF(M14>90,"A",IF(M14>80,"B",IF(M14>70,"C",IF(M14>=33,"D","E")))) -> D | O14: =IF(M14>=33, "Pass", "Fail") -> Pass
B15: HSC10 | C15: Amar | D15: 66 | E15: 90 | F15: 76 | G15: 40 | H15: 60 | I15: 75 | J15: =MIN(D15:I15) -> 40 | K15: =MAX(D15:I15) -> 90 | L15: =SUM(D15:I15) -> 407 | M15: =AVERAGE(D15:I15) -> 67.833333 | N15: =IF(M15>90,"A",IF(M15>80,"B",IF(M15>70,"C",IF(M15>=33,"D","E")))) -> D | O15: =IF(M15>=33, "Pass", "Fail") -> Pass

Sheet Result Sheet
A1: Result Sheet
A5: Roll No | B5: HSC01
A6: Student Name | B6: =IF(B5="","",VLOOKUP(B5,'Teacher''s Sheet'!$B$5:$O$15,2,FALSE)) -> Krish
A8: Subject | B8: Total marks | C8: Obtain marks
A9: Physics | B9: 100 | C9: =IF(B5="","",VLOOKUP(B5,'Teacher''s Sheet'!$B$5:$O$15,3,FALSE)) -> 99
A10: Chemistry | B10: 100 | C10: =IF(B5="","",VLOOKUP(B5,'Teacher''s Sheet'!$B$5:$O$15,4,FALSE)) -> 97
A11: Maths | B11: 100 | C11: =IF(B5="","",VLOOKUP(B5,'Teacher''s Sheet'!$B$5:$O$15,5,FALSE)) -> 100
A12: Biology | B12: 100 | C12: =IF(B5="","",VLOOKUP(B5,'Teacher''s Sheet'!$B$5:$O$15,6,FALSE)) -> 80
A13: English | B13: 100 | C13: =IF(B5="","",VLOOKUP(B5,'Teacher''s Sheet'!$B$5:$O$15,7,FALSE)) -> 86
A14: Computer | B14: 100 | C14: =IF(B5="","",VLOOKUP(B5,'Teacher''s Sheet'!$B$5:$O$15,8,FALSE)) -> 100
A16: Total Marks | B16: =SUM(B9:B14) -> 600 | C16: =IF(B5="","",VLOOKUP(B5,'Teacher''s Sheet'!$B$5:$O$15,11,FALSE)) -> 562
A17: Average | B17: =IF(B5="","",VLOOKUP(B5,'Teacher''s Sheet'!$B$5:$O$15,12,FALSE)) -> 93.666667
A18: Grade | B18: =IF(B5="","",VLOOKUP(B5,'Teacher''s Sheet'!$B$5:$O$15,13,FALSE)) -> A
A19: Result | B19: =IF(B5="","",VLOOKUP(B5,'Teacher''s Sheet'!$B$5:$O$15,14,FALSE)) -> Pass
A26: Word file | B26: Link

Sheet Salary data
A3: Job Title | B3: Code | C3: Basic Salary | D3: DA | E3: TA | F3: HRA | G3: PF | H3: PT
A4: Business Head | B4: BH | C4: 100000 | D4: 0.12 | E4: 0.12 | F4: 9500 | G4: 0.15 | H4: 0.15
A5: Data Scientist | B5: DS | C5: 90000 | D5: 0.12 | E5: 0.12 | F5: 9500 | G5: 0.15 | H5: 0.15
A6: Data Analyst | B6: DA | C6: 80000 | D6: 0.1 | E6: 0.1 | F6: 6500 | G6: 0.12 | H6: 0.12
A7: AI Enginner | B7: AE | C7: 95000 | D7: 0.1 | E7: 0.1 | F7: 6500 | G7: 0.12 | H7: 0.12
A8: Python Developer | B8: PD | C8: 85000 | D8: 0.1 | E8: 0.1 | F8: 6500 | G8: 0.12 | H8: 0.12
A9: Marketing Manager | B9: MM | C9: 70000 | D9: 0.1 | E9: 0.1 | F9: 6500 | G9: 0.12 | H9: 0.12
A10: General Manager | B10: GM | C10: 75000 | D10: 0.1 | E10: 0.1 | F10: 6500 | G10: 0.12 | H10: 0.12
A11: Accountant | B11: AC | C11: 90000 | D11: 0.08 | E11: 0.08 | F11: 5500 | G11: 0.1 | H11: 0.1
A12: Security Guard | B12: SG | C12: 50000 | D12: 0.06 | E12: 0.06 | F12: 4500 | G12: 0.1 | H12: 0.1

Sheet Salary sheet
A6: Employee name | B6: Code | C6: Basic Salary | D6: DA | E6: TA | F6: HRA | G6: PF | H6: PT | I6: Gross
A7: Krish | B7: BH | C7: =IF(B7="","",IF(B7="BH",100000,IF(B7="DS",90000,IF(B7="DA",80000,IF(B7="AE",95000,IF(B7="PD",85000,IF(B7="MM",70000,IF(B7="GM",75000,IF(B7="AC",90000,IF(B7="SG",50000,"")))))))))) -> 100000 | D7: =IF(B7="","",IF(B7="BH",100000*12%,IF(B7="DS",90000*12%,IF(B7="DA",80000*10%,IF(B7="AE",95000*10%,IF(B7="PD",85000*10%,IF(B7="MM",70000*10%,IF(B7="GM",75000*10%,IF(B7="AC",90000*8%,IF(B7="SG",50000*6%,"")))))))))) -> 12000 | E7: =IF(B7="","",IF(B7="BH",100000*12%,IF(B7="DS",90000*12%,IF(B7="DA",80000*10%,IF(B7="AE",95000*10%,IF(B7="PD",85000*10%,IF(B7="MM",70000*10%,IF(B7="GM",75000*10%,IF(B7="AC",90000*8%,IF(B7="SG",50000*6%,"")))))))))) -> 12000 | F7: =IF(B7="","",IF(B7="BH",9500,IF(B7="DS",9500,IF(B7="DA",6500,IF(B7="AE",6500,IF(B7="PD",6500,IF(B7="MM",6500,IF(B7="GM",6500,IF(B7="AC",5500,IF(B7="SG",4500,"")))))))))) -> 9500 | G7: =IF(B7="","",IF(B7="BH",100000*15%,IF(B7="DS",90000*15%,IF(B7="DA",80000*12%,IF(B7="AE",95000*12%,IF(B7="PD",85000*12%,IF(B7="MM",70000*12%,IF(B7="GM",75000*12%,IF(B7="AC",90000*10%,IF(B7="SG",50000*10%,"")))))))))) -> 15000 | H7: =IF(B7="","",IF(B7="BH",100000*15%,IF(B7="DS",90000*15%,IF(B7="DA",80000*12%,IF(B7="AE",95000*12%,IF(B7="PD",85000*12%,IF(B7="MM",70000*12%,IF(B7="GM",75000*12%,IF(B7="AC",90000*10%,IF(B7="SG",50000*10%,"")))))))))) -> 15000 | I7: =IF(B7="","",C7+D7+E7+F7-G7-H7) -> 103500
A8: Dhiren | B8: DS | C8: =IF(B8="","",IF(B8="BH",100000,IF(B8="DS",90000,IF(B8="DA",80000,IF(B8="AE",95000,IF(B8="PD",85000,IF(B8="MM",70000,IF(B8="GM",75000,IF(B8="AC",90000,IF(B8="SG",50000,"")))))))))) -> 90000 | D8: =IF(B8="","",IF(B8="BH",100000*12%,IF(B8="DS",90000*12%,IF(B8="DA",80000*10%,IF(B8="AE",95000*10%,IF(B8="PD",85000*10%,IF(B8="MM",70000*10%,IF(B8="GM",75000*10%,IF(B8="AC",90000*8%,IF(B8="SG",50000*6%,"")))))))))) -> 10800 | E8: =IF(B8="","",IF(B8="BH",100000*12%,IF(B8="DS",90000*12%,IF(B8="DA",80000*10%,IF(B8="AE",95000*10%,IF(B8="PD",85000*10%,IF(B8="MM",70000*10%,IF(B8="GM",75000*10%,IF(B8="AC",90000*8%,IF(B8="SG",50000*6%,"")))))))))) -> 10800 | F8: =IF(B8="","",IF(B8="BH",9500,IF(B8="DS",9500,IF(B8="DA",6500,IF(B8="AE",6500,IF(B8="PD",6500,IF(B8="MM",6500,IF(B8="GM",6500,IF(B8="AC",5500,IF(B8="SG",4500,"")))))))))) -> 9500 | G8: =IF(B8="","",IF(B8="BH",100000*15%,IF(B8="DS",90000*15%,IF(B8="DA",80000*12%,IF(B8="AE",95000*12%,IF(B8="PD",85000*12%,IF(B8="MM",70000*12%,IF(B8="GM",75000*12%,IF(B8="AC",90000*10%,IF(B8="SG",50000*10%,"")))))))))) -> 13500 | H8: =IF(B8="","",IF(B8="BH",100000*15%,IF(B8="DS",90000*15%,IF(B8="DA",80000*12%,IF(B8="AE",95000*12%,IF(B8="PD",85000*12%,IF(B8="MM",70000*12%,IF(B8="GM",75000*12%,IF(B8="AC",90000*10%,IF(B8="SG",50000*10%,"")))))))))) -> 13500 | I8: =IF(B8="","",C8+D8+E8+F8-G8-H8) -> 94100
A9: Shubham | B9: DA | C9: =IF(B9="","",IF(B9="BH",100000,IF(B9="DS",90000,IF(B9="DA",80000,IF(B9="AE",95000,IF(B9="PD",85000,IF(B9="MM",70000,IF(B9="GM",75000,IF(B9="AC",90000,IF(B9="SG",50000,"")))))))))) -> 80000 | D9: =IF(B9="","",IF(B9="BH",100000*12%,IF(B9="DS",90000*12%,IF(B9="DA",80000*10%,IF(B9="AE",95000*10%,IF(B9="PD",85000*10%,IF(B9="MM",70000*10%,IF(B9="GM",75000*10%,IF(B9="AC",90000*8%,IF(B9="SG",50000*6%,"")))))))))) -> 8000 | E9: =IF(B9="","",IF(B9="BH",100000*12%,IF(B9="DS",90000*12%,IF(B9="DA",80000*10%,IF(B9="AE",95000*10%,IF(B9="PD",85000*10%,IF(B9="MM",70000*10%,IF(B9="GM",75000*10%,IF(B9="AC",90000*8%,IF(B9="SG",50000*6%,"")))))))))) -> 8000 | F9: =IF(B9="","",IF(B9="BH",9500,IF(B9="DS",9500,IF(B9="DA",6500,IF(B9="AE",6500,IF(B9="PD",6500,IF(B9="MM",6500,IF(B9="GM",6500,IF(B9="AC",5500,IF(B9="SG",4500,"")))))))))) -> 6500 | G9: =IF(B9="","",IF(B9="BH",100000*15%,IF(B9="DS",90000*15%,IF(B9="DA",80000*12%,IF(B9="AE",95000*12%,IF(B9="PD",85000*12%,IF(B9="MM",70000*12%,IF(B9="GM",75000*12%,IF(B9="AC",90000*10%,IF(B9="SG",50000*10%,"")))))))))) -> 9600 | H9: =IF(B9="","",IF(B9="BH",100000*15%,IF(B9="DS",90000*15%,IF(B9="DA",80000*12%,IF(B9="AE",95000*12%,IF(B9="PD",85000*12%,IF(B9="MM",70000*12%,IF(B9="GM",75000*12%,IF(B9="AC",90000*10%,IF(B9="SG",50000*10%,"")))))))))) -> 9600 | I9: =IF(B9="","",C9+D9+E9+F9-G9-H9) -> 83300
A13: Employee Name | B13: Code | C13: Basic Salary | D13: DA | E13: TA | F13: HRA | G13: PF | H13: PT | I13: Gross
A14: Krish | B14: BH | C14: =IF(B14="","",VLOOKUP(B14,'Salary data'!$B$3:$H$12,2,FALSE)) -> 100000 | D14: =IF(B14="","",C14*VLOOKUP(B14,'Salary data'!$B$3:$H$12,3,FALSE)) -> 12000 | E14: =IF(B14="","",C14*VLOOKUP(B14,'Salary data'!$B$3:$H$12,4,FALSE)) -> 12000 | F14: =IF(B14="","",VLOOKUP(B14,'Salary data'!$B$3:$H$12,5,FALSE)) -> 9500 | G14: =IF(B14="","",C14*VLOOKUP(B14,'Salary data'!$B$3:$H$12,6,FALSE)) -> 15000 | H14: =IF(B14="","",C14*VLOOKUP(B14,'Salary data'!$B$3:$H$12,7,FALSE)) -> 15000 | I14: =IF(B14="","",C14+D14+E14+F14-G14-H14) -> 103500
A15: Dhiren | B15: DS | C15: =IF(B15="","",VLOOKUP(B15,'Salary data'!$B$3:$H$12,2,FALSE)) -> 90000 | D15: =IF(B15="","",C15*VLOOKUP(B15,'Salary data'!$B$3:$H$12,3,FALSE)) -> 10800 | E15: =IF(B15="","",C15*VLOOKUP(B15,'Salary data'!$B$3:$H$12,4,FALSE)) -> 10800 | F15: =IF(B15="","",VLOOKUP(B15,'Salary data'!$B$3:$H$12,5,FALSE)) -> 9500 | G15: =IF(B15="","",C15*VLOOKUP(B15,'Salary data'!$B$3:$H$12,6,FALSE)) -> 13500 | H15: =IF(B15="","",C15*VLOOKUP(B15,'Salary data'!$B$3:$H$12,7,FALSE)) -> 13500 | I15: =IF(B15="","",C15+D15+E15+F15-G15-H15) -> 94100
A16: Shubham | B16: DA | C16: =IF(B16="","",VLOOKUP(B16,'Salary data'!$B$3:$H$12,2,FALSE)) -> 80000 | D16: =IF(B16="","",C16*VLOOKUP(B16,'Salary data'!$B$3:$H$12,3,FALSE)) -> 8000 | E16: =IF(B16="","",C16*VLOOKUP(B16,'Salary data'!$B$3:$H$12,4,FALSE)) -> 8000 | F16: =IF(B16="","",VLOOKUP(B16,'Salary data'!$B$3:$H$12,5,FALSE)) -> 6500 | G16: =IF(B16="","",C16*VLOOKUP(B16,'Salary data'!$B$3:$H$12,6,FALSE)) -> 9600 | H16: =IF(B16="","",C16*VLOOKUP(B16,'Salary data'!$B$3:$H$12,7,FALSE)) -> 9600 | I16: =IF(B16="","",C16+D16+E16+F16-G16-H16) -> 83300

Sheet Product Sheet
B4: Product No. | C4: Product Name | D4: Price | E4: GST
B5: A101 | C5: MousePad | D5: 461 | E5: 0.28
B6: A102 | C6: Logitech Keyboard | D6: 452 | E6: 0.29
B7: A103 | C7: Logitech Mouse | D7: 178 | E7: 0.11
B8: A104 | C8: Samsung S24 Ultra | D8: 299 | E8: 0.26
B9: A105 | C9: Samsung SSD 1TB | D9: 449 | E9: 0.12
B10: A106 | C10: Acer Monitor | D10: 357 | E10: 0.25
B11: A107 | C11: Samsung Monitor | D11: 498 | E11: 0.24
B12: A108 | C12: DDR5 Ram 16 GB | D12: 385 | E12: 0.29
B13: A109 | C13: MotherBoard | D13: 83 | E13: 0.05
B14: A110 | C14: MSI Laptop | D14: 468 | E14: 0.21
B15: A111 | C15: Macbook | D15: 203 | E15: 0.28
B16: A112 | C16: IMAC | D16: 436 | E16: 0.22
... B104: A200 | C104: Windows11 Pro Key | D104: 339 | E104: 0.28

Sheet Billing + GST
B2: Billing + GST
B4: Sr. No | C4: Product No. | D4: Product Name | E4: Price | F4: GST | G4: Net Price | H4: Quantity | I4: Amount
B5: 1 | C5: A101 | D5: =IF(C5="","",VLOOKUP(C5,'Product Sheet'!$B$4:$E$104,2,FALSE)) -> MousePad | E5: =IF(C5="","",VLOOKUP(C5,'Product Sheet'!$B$4:$E$104,3,FALSE)) -> 461 | F5: =IF(C5="","",E5*VLOOKUP(C5,'Product Sheet'!$B$4:$E$104,4,FALSE)) -> 129.08 | G5: =E5+F5 -> 590.08 | H5: 10 | I5: =G5*H5 -> 5900.8
B6: 2 | C6: A102 | D6: =IF(C6="","",VLOOKUP(C6,'Product Sheet'!$B$4:$E$104,2,FALSE)) -> Logitech Keyboard | E6: =IF(C6="","",VLOOKUP(C6,'Product Sheet'!$B$4:$E$104,3,FALSE)) -> 452 | F6: =IF(C6="","",E6*VLOOKUP(C6,'Product Sheet'!$B$4:$E$104,4,FALSE)) -> 131.08 | G6: =E6+F6 -> 583.08 | H6: 7 | I6: =G6*H6 -> 4081.56
B7: 3 | C7: A103 | D7: =IF(C7="","",VLOOKUP(C7,'Product Sheet'!$B$4:$E$104,2,FALSE)) -> Logitech Mouse | E7: =IF(C7="","",VLOOKUP(C7,'Product Sheet'!$B$4:$E$104,3,FALSE)) -> 178 | F7: =IF(C7="","",E7*VLOOKUP(C7,'Product Sheet'!$B$4:$E$104,4,FALSE)) -> 19.58 | G7: =E7+F7 -> 197.58 | H7: 3 | I7: =G7*H7 -> 592.74
B8: 4 | C8: A104 | D8: =IF(C8="","",VLOOKUP(C8,'Product Sheet'!$B$4:$E$104,2,FALSE)) -> Samsung S24 Ultra | E8: =IF(C8="","",VLOOKUP(C8,'Product Sheet'!$B$4:$E$104,3,FALSE)) -> 299 | F8: =IF(C8="","",E8*VLOOKUP(C8,'Product Sheet'!$B$4:$E$104,4,FALSE)) -> 77.74 | G8: =E8+F8 -> 376.74 | H8: 9 | I8: =G8*H8 -> 3390.66
B9: 5 | C9: A105 | D9: =IF(C9="","",VLOOKUP(C9,'Product Sheet'!$B$4:$E$104,2,FALSE)) -> Samsung SSD 1TB | E9: =IF(C9="","",VLOOKUP(C9,'Product Sheet'!$B$4:$E$104,3,FALSE)) -> 449 | F9: =IF(C9="","",E9*VLOOKUP(C9,'Product Sheet'!$B$4:$E$104,4,FALSE)) -> 53.88 | G9: =E9+F9 -> 502.88 | H9: 2 | I9: =G9*H9 -> 1005.76
B10: 6 | C10: A106 | D10: =IF(C10="","",VLOOKUP(C10,'Product Sheet'!$B$4:$E$104,2,FALSE)) -> Acer Monitor | E10: =IF(C10="","",VLOOKUP(C10,'Product Sheet'!$B$4:$E$104,3,FALSE)) -> 357 | F10: =IF(C10="","",E10*VLOOKUP(C10,'Product Sheet'!$B$4:$E$104,4,FALSE)) -> 89.25 | G10: =E10+F10 -> 446.25 | H10: 10 | I10: =G10*H10 -> 4462.5
B11: 7 | C11: A107 | D11: =IF(C11="","",VLOOKUP(C11,'Product Sheet'!$B$4:$E$104,2,FALSE)) -> Samsung Monitor | E11: =IF(C11="","",VLOOKUP(C11,'Product Sheet'!$B$4:$E$104,3,FALSE)) -> 498 | F11: =IF(C11="","",E11*VLOOKUP(C11,'Product Sheet'!$B$4:$E$104,4,FALSE)) -> 119.52 | G11: =E11+F11 -> 617.52 | H11: 3 | I11: =G11*H11 -> 1852.56
B12: 8 | C12: A108 | D12: =IF(C12="","",VLOOKUP(C12,'Product Sheet'!$B$4:$E$104,2,FALSE)) -> DDR5 Ram 16 GB | E12: =IF(C12="","",VLOOKUP(C12,'Product Sheet'!$B$4:$E$104,3,FALSE)) -> 385 | F12: =IF(C12="","",E12*VLOOKUP(C12,'Product Sheet'!$B$4:$E$104,4,FALSE)) -> 111.65 | G12: =E12+F12 -> 496.65 | H12: 7 | I12: =G12*H12 -> 3476.55
B13: 9 | C13: A109 | D13: =IF(C13="","",VLOOKUP(C13,'Product Sheet'!$B$4:$E$104,2,FALSE)) -> MotherBoard | E13: =IF(C13="","",VLOOKUP(C13,'Product Sheet'!$B$4:$E$104,3,FALSE)) -> 83 | F13: =IF(C13="","",E13*VLOOKUP(C13,'Product Sheet'!$B$4:$E$104,4,FALSE)) -> 4.15 | G13: =E13+F13 -> 87.15 | H13: 7 | I13: =G13*H13 -> 610.05
B14: 10 | C14: A110 | D14: =IF(C14="","",VLOOKUP(C14,'Product Sheet'!$B$4:$E$104,2,FALSE)) -> MSI Laptop | E14: =IF(C14="","",VLOOKUP(C14,'Product Sheet'!$B$4:$E$104,3,FALSE)) -> 468 | F14: =IF(C14="","",E14*VLOOKUP(C14,'Product Sheet'!$B$4:$E$104,4,FALSE)) -> 98.28 | G14: =E14+F14 -> 566.28 | H14: 5 | I14: =G14*H14 -> 2831.4
B15: 11 | C15: A111 | D15: =IF(C15="","",VLOOKUP(C15,'Product Sheet'!$B$4:$E$104,2,FALSE)) -> Macbook | E15: =IF(C15="","",VLOOKUP(C15,'Product Sheet'!$B$4:$E$104,3,FALSE)) -> 203 | F15: =IF(C15="","",E15*VLOOKUP(C15,'Product Sheet'!$B$4:$E$104,4,FALSE)) -> 56.84 | G15: =E15+F15 -> 259.84 | H15: 5 | I15: =G15*H15 -> 1299.2
B16: 12 | C16: A112 | D16: =IF(C16="","",VLOOKUP(C16,'Product Sheet'!$B$4:$E$104,2,FALSE)) -> IMAC | E16: =IF(C16="","",VLOOKUP(C16,'Product Sheet'!$B$4:$E$104,3,FALSE)) -> 436 | F16: =IF(C16="","",E16*VLOOKUP(C16,'Product Sheet'!$B$4:$E$104,4,FALSE)) -> 95.92 | G16: =E16+F16 -> 531.92 | H16: 8 | I16: =G16*H16 -> 4255.36
... B104: 100 | C104: A200 | D104: =IF(C104="","",VLOOKUP(C104,'Product Sheet'!$B$4:$E$104,2,FALSE)) -> Windows11 Pro Key | E104: =IF(C104="","",VLOOKUP(C104,'Product Sheet'!$B$4:$E$104,3,FALSE)) -> 339 | F104: =IF(C104="","",E104*VLOOKUP(C104,'Product Sheet'!$B$4:$E$104,4,FALSE)) -> 94.92 | G104: =E104+F104 -> 433.92 | H104: 8 | I104: =G104*H104 -> 3471.36

Sheet Product Discount
B2: ProductNo. | C2: Product Name | D2: MRP | E2: Discount | F2: Net price
B3: A101 | C3: =IF(B3="","",VLOOKUP(B3,'Product Sheet'!$B$4:$D$104,2,FALSE)) -> MousePad | D3: =IF(B3="","",VLOOKUP(B3,'Product Sheet'!$B$4:$D$104,3,FALSE)) -> 461 | E3: 0.39 | F3: =IF(B3="","",(D3-D3*E3)) -> 281.21
B4: A102 | C4: =IF(B4="","",VLOOKUP(B4,'Product Sheet'!$B$4:$D$104,2,FALSE)) -> Logitech Keyboard | D4: =IF(B4="","",VLOOKUP(B4,'Product Sheet'!$B$4:$D$104,3,FALSE)) -> 452 | E4: 0.37 | F4: =IF(B4="","",(D4-D4*E4)) -> 284.76
B5: A103 | C5: =IF(B5="","",VLOOKUP(B5,'Product Sheet'!$B$4:$D$104,2,FALSE)) -> Logitech Mouse | D5: =IF(B5="","",VLOOKUP(B5,'Product Sheet'!$B$4:$D$104,3,FALSE)) -> 178 | E5: 0.3 | F5: =IF(B5="","",(D5-D5*E5)) -> 124.6
B6: A104 | C6: =IF(B6="","",VLOOKUP(B6,'Product Sheet'!$B$4:$D$104,2,FALSE)) -> Samsung S24 Ultra | D6: =IF(B6="","",VLOOKUP(B6,'Product Sheet'!$B$4:$D$104,3,FALSE)) -> 299 | E6: 0.3 | F6: =IF(B6="","",(D6-D6*E6)) -> 209.3
B7: A105 | C7: =IF(B7="","",VLOOKUP(B7,'Product Sheet'!$B$4:$D$104,2,FALSE)) -> Samsung SSD 1TB | D7: =IF(B7="","",VLOOKUP(B7,'Product Sheet'!$B$4:$D$104,3,FALSE)) -> 449 | E7: 0.37 | F7: =IF(B7="","",(D7-D7*E7)) -> 282.87
B8: A106 | C8: =IF(B8="","",VLOOKUP(B8,'Product Sheet'!$B$4:$D$104,2,FALSE)) -> Acer Monitor | D8: =IF(B8="","",VLOOKUP(B8,'Product Sheet'!$B$4:$D$104,3,FALSE)) -> 357 | E8: 0.28 | F8: =IF(B8="","",(D8-D8*E8)) -> 257.04
B9: A107 | C9: =IF(B9="","",VLOOKUP(B9,'Product Sheet'!$B$4:$D$104,2,FALSE)) -> Samsung Monitor | D9: =IF(B9="","",VLOOKUP(B9,'Product Sheet'!$B$4:$D$104,3,FALSE)) -> 498 | E9: 0.18 | F9: =IF(B9="","",(D9-D9*E9)) -> 408.36
B10: A108 | C10: =IF(B10="","",VLOOKUP(B10,'Product Sheet'!$B$4:$D$104,2,FALSE)) -> DDR5 Ram 16 GB | D10: =IF(B10="","",VLOOKUP(B10,'Product Sheet'!$B$4:$D$104,3,FALSE)) -> 385 | E10: 0.4 | F10: =IF(B10="","",(D10-D10*E10)) -> 231
B11: A109 | C11: =IF(B11="","",VLOOKUP(B11,'Product Sheet'!$B$4:$D$104,2,FALSE)) -> MotherBoard | D11: =IF(B11="","",VLOOKUP(B11,'Product Sheet'!$B$4:$D$104,3,FALSE)) -> 83 | E11: 0.43 | F11: =IF(B11="","",(D11-D11*E11)) -> 47.31
B12: A110 | C12: =IF(B12="","",VLOOKUP(B12,'Product Sheet'!$B$4:$D$104,2,FALSE)) -> MSI Laptop | D12: =IF(B12="","",VLOOKUP(B12,'Product Sheet'!$B$4:$D$104,3,FALSE)) -> 468 | E12: 0.23 | F12: =IF(B12="","",(D12-D12*E12)) -> 360.36
B13: A111 | C13: =IF(B13="","",VLOOKUP(B13,'Product Sheet'!$B$4:$D$104,2,FALSE)) -> Macbook | D13: =IF(B13="","",VLOOKUP(B13,'Product Sheet'!$B$4:$D$104,3,FALSE)) -> 203 | E13: 0.28 | F13: =IF(B13="","",(D13-D13*E13)) -> 146.16
B14: A112 | C14: =IF(B14="","",VLOOKUP(B14,'Product Sheet'!$B$4:$D$104,2,FALSE)) -> IMAC | D14: =IF(B14="","",VLOOKUP(B14,'Product Sheet'!$B$4:$D$104,3,FALSE)) -> 436 | E14: 0.13 | F14: =IF(B14="","",(D14-D14*E14)) -> 379.32
... B102: A200 | C102: =IF(B102="","",VLOOKUP(B102,'Product Sheet'!$B$4:$D$104,2,FALSE)) -> Windows11 Pro Key | D102: =IF(B102="","",VLOOKUP(B102,'Product Sheet'!$B$4:$D$104,3,FALSE)) -> 339 | E102: 0.38 | F102: =IF(B102="","",(D102-D102*E102)) -> 210.18

Sheet Product Discount GST
B4: Product No. | C4: Product Name | D4: MRP | E4: Quantity | F4: Discount | G4: Price | H4: GST | I4: Net Amount
B5: A101 | C5: =IF(B5="","",VLOOKUP(B5,'Product Sheet'!$B$4:$E$104,2,FALSE)) -> MousePad | D5: =IF(B5="","",VLOOKUP(B5,'Product Sheet'!$B$4:$E$104,3,FALSE)) -> 461 | E5: 10 | F5: 0.39 | G5: =D5-D5*F5 -> 281.21 | H5: =IF(B5="","",D5*VLOOKUP(B5,'Product Sheet'!$B$4:$E$104,4,FALSE)) -> 129.08 | I5: =(G5+H5)*E5 -> 4102.9
B6: A102 | C6: =IF(B6="","",VLOOKUP(B6,'Product Sheet'!$B$4:$E$104,2,FALSE)) -> Logitech Keyboard | D6: =IF(B6="","",VLOOKUP(B6,'Product Sheet'!$B$4:$E$104,3,FALSE)) -> 452 | E6: 7 | F6: 0.37 | G6: =D6-D6*F6 -> 284.76 | H6: =IF(B6="","",D6*VLOOKUP(B6,'Product Sheet'!$B$4:$E$104,4,FALSE)) -> 131.08 | I6: =(G6+H6)*E6 -> 2910.88
B7: A103 | C7: =IF(B7="","",VLOOKUP(B7,'Product Sheet'!$B$4:$E$104,2,FALSE)) -> Logitech Mouse | D7: =IF(B7="","",VLOOKUP(B7,'Product Sheet'!$B$4:$E$104,3,FALSE)) -> 178 | E7: 3 | F7: 0.3 | G7: =D7-D7*F7 -> 124.6 | H7: =IF(B7="","",D7*VLOOKUP(B7,'Product Sheet'!$B$4:$E$104,4,FALSE)) -> 19.58 | I7: =(G7+H7)*E7 -> 432.54
B8: A104 | C8: =IF(B8="","",VLOOKUP(B8,'Product Sheet'!$B$4:$E$104,2,FALSE)) -> Samsung S24 Ultra | D8: =IF(B8="","",VLOOKUP(B8,'Product Sheet'!$B$4:$E$104,3,FALSE)) -> 299 | E8: 9 | F8: 0.3 | G8: =D8-D8*F8 -> 209.3 | H8: =IF(B8="","",D8*VLOOKUP(B8,'Product Sheet'!$B$4:$E$104,4,FALSE)) -> 77.74 | I8: =(G8+H8)*E8 -> 2583.36
B9: A105 | C9: =IF(B9="","",VLOOKUP(B9,'Product Sheet'!$B$4:$E$104,2,FALSE)) -> Samsung SSD 1TB | D9: =IF(B9="","",VLOOKUP(B9,'Product Sheet'!$B$4:$E$104,3,FALSE)) -> 449 | E9: 2 | F9: 0.37 | G9: =D9-D9*F9 -> 282.87 | H9: =IF(B9="","",D9*VLOOKUP(B9,'Product Sheet'!$B$4:$E$104,4,FALSE)) -> 53.88 | I9: =(G9+H9)*E9 -> 673.5
B10: A106 | C10: =IF(B10="","",VLOOKUP(B10,'Product Sheet'!$B$4:$E$104,2,FALSE)) -> Acer Monitor | D10: =IF(B10="","",VLOOKUP(B10,'Product Sheet'!$B$4:$E$104,3,FALSE)) -> 357 | E10: 10 | F10: 0.28 | G10: =D10-D10*F10 -> 257.04 | H10: =IF(B10="","",D10*VLOOKUP(B10,'Product Sheet'!$B$4:$E$104,4,FALSE)) -> 89.25 | I10: =(G10+H10)*E10 -> 3462.9
B11: A107 | C11: =IF(B11="","",VLOOKUP(B11,'Product Sheet'!$B$4:$E$104,2,FALSE)) -> Samsung Monitor | D11: =IF(B11="","",VLOOKUP(B11,'Product Sheet'!$B$4:$E$104,3,FALSE)) -> 498 | E11: 3 | F11: 0.18 | G11: =D11-D11*F11 -> 408.36 | H11: =IF(B11="","",D11*VLOOKUP(B11,'Product Sheet'!$B$4:$E$104,4,FALSE)) -> 119.52 | I11: =(G11+H11)*E11 -> 1583.64
B12: A108 | C12: =IF(B12="","",VLOOKUP(B12,'Product Sheet'!$B$4:$E$104,2,FALSE)) -> DDR5 Ram 16 GB | D12: =IF(B12="","",VLOOKUP(B12,'Product Sheet'!$B$4:$E$104,3,FALSE)) -> 385 | E12: 7 | F12: 0.4 | G12: =D12-D12*F12 -> 231 | H12: =IF(B12="","",D12*VLOOKUP(B12,'Product Sheet'!$B$4:$E$104,4,FALSE)) -> 111.65 | I12: =(G12+H12)*E12 -> 2398.55
B13: A109 | C13: =IF(B13="","",VLOOKUP(B13,'Product Sheet'!$B$4:$E$104,2,FALSE)) -> MotherBoard | D13: =IF(B13="","",VLOOKUP(B13,'Product Sheet'!$B$4:$E$104,3,FALSE)) -> 83 | E13: 7 | F13: 0.43 | G13: =D13-D13*F13 -> 47.31 | H13: =IF(B13="","",D13*VLOOKUP(B13,'Product Sheet'!$B$4:$E$104,4,FALSE)) -> 4.15 | I13: =(G13+H13)*E13 -> 360.22
B14: A110 | C14: =IF(B14="","",VLOOKUP(B14,'Product Sheet'!$B$4:$E$104,2,FALSE)) -> MSI Laptop | D14: =IF(B14="","",VLOOKUP(B14,'Product Sheet'!$B$4:$E$104,3,FALSE)) -> 468 | E14: 5 | F14: 0.23 | G14: =D14-D14*F14 -> 360.36 | H14: =IF(B14="","",D14*VLOOKUP(B14,'Product Sheet'!$B$4:$E$104,4,FALSE)) -> 98.28 | I14: =(G14+H14)*E14 -> 2293.2
B15: A111 | C15: =IF(B15="","",VLOOKUP(B15,'Product Sheet'!$B$4:$E$104,2,FALSE)) -> Macbook | D15: =IF(B15="","",VLOOKUP(B15,'Product Sheet'!$B$4:$E$104,3,FALSE)) -> 203 | E15: 5 | F15: 0.28 | G15: =D15-D15*F15 -> 146.16 | H15: =IF(B15="","",D15*VLOOKUP(B15,'Product Sheet'!$B$4:$E$104,4,FALSE)) -> 56.84 | I15: =(G15+H15)*E15 -> 1015
B16: A112 | C16: =IF(B16="","",VLOOKUP(B16,'Product Sheet'!$B$4:$E$104,2,FALSE)) -> IMAC | D16: =IF(B16="","",VLOOKUP(B16,'Product Sheet'!$B$4:$E$104,3,FALSE)) -> 436 | E16: 8 | F16: 0.13 | G16: =D16-D16*F16 -> 379.32 | H16: =IF(B16="","",D16*VLOOKUP(B16,'Product Sheet'!$B$4:$E$104,4,FALSE)) -> 95.92 | I16: =(G16+H16)*E16 -> 3801.92
... B104: A200 | C104: =IF(B104="","",VLOOKUP(B104,'Product Sheet'!$B$4:$E$104,2,FALSE)) -> Windows11 Pro Key | D104: =IF(B104="","",VLOOKUP(B104,'Product Sheet'!$B$4:$E$104,3,FALSE)) -> 339 | E104: 8 | F104: 0.38 | G104: =D104-D104*F104 -> 210.18 | H104: =IF(B104="","",D104*VLOOKUP(B104,'Product Sheet'!$B$4:$E$104,4,FALSE)) -> 94.92 | I104: =(G104+H104)*E104 -> 2440.8

Sheet Employee In_out time
B1: Employee Attendence Sheet
B3: Name | C3: Krish | D3: Month | E3: January | F3: Salary | G3: 35000
B4: Date | C4: Day | D4: Intime | E4: Outtime | F4: Working Hour | G4: Late Mark
B5: 46023 | C5: =TEXT(B5,"ddd") -> Thu | D5: 0.375 | E5: 0.75 | F5: =E5-D5 -> 0.375 | G5: =IF(F5="","",IF(F5<TIME(9,0,0),"LM",IF(F5="L","L","NO LM"))) -> NO LM
B6: 46024 | C6: =TEXT(B6,"ddd") -> Fri | D6: 0.45833333 | E6: 0.75 | F6: =E6-D6 -> 0.29166667 | G6: =IF(F6="","",IF(F6<TIME(9,0,0),"LM",IF(F6="L","L","NO LM"))) -> LM
B7: 46025 | C7: =TEXT(B7,"ddd") -> Sat | D7: 0.375 | E7: 0.75 | F7: =E7-D7 -> 0.375 | G7: =IF(F7="","",IF(F7<TIME(9,0,0),"LM",IF(F7="L","L","NO LM"))) -> NO LM
B8: 46026 | C8: =TEXT(B8,"ddd") -> Sun | D8: L | E8: L | F8: L | G8: =IF(F8="","",IF(F8<TIME(9,0,0),"LM",IF(F8="L","L","NO LM"))) -> L
B9: 46027 | C9: =TEXT(B9,"ddd") -> Mon | D9: 0.375 | E9: 0.75 | F9: =E9-D9 -> 0.375 | G9: =IF(F9="","",IF(F9<TIME(9,0,0),"LM",IF(F9="L","L","NO LM"))) -> NO LM
B10: 46028 | C10: =TEXT(B10,"ddd") -> Tue | D10: 0.39583333 | E10: 0.75 | F10: =E10-D10 -> 0.35416667 | G10: =IF(F10="","",IF(F10<TIME(9,0,0),"LM",IF(F10="L","L","NO LM"))) -> LM
B11: 46029 | C11: =TEXT(B11,"ddd") -> Wed | D11: 0.375 | E11: 0.75 | F11: =E11-D11 -> 0.375 | G11: =IF(F11="","",IF(F11<TIME(9,0,0),"LM",IF(F11="L","L","NO LM"))) -> NO LM
B12: 46030 | C12: =TEXT(B12,"ddd") -> Thu | D12: 0.375 | E12: 0.75 | F12: =E12-D12 -> 0.375 | G12: =IF(F12="","",IF(F12<TIME(9,0,0),"LM",IF(F12="L","L","NO LM"))) -> NO LM
B13: 46031 | C13: =TEXT(B13,"ddd") -> Fri | D13: 0.375 | E13: 0.75 | F13: =E13-D13 -> 0.375 | G13: =IF(F13="","",IF(F13<TIME(9,0,0),"LM",IF(F13="L","L","NO LM"))) -> NO LM
B14: 46032 | C14: =TEXT(B14,"ddd") -> Sat | D14: 0.39236111 | E14: 0.75 | F14: =E14-D14 -> 0.35763889 | G14: =IF(F14="","",IF(F14<TIME(9,0,0),"LM",IF(F14="L","L","NO LM"))) -> LM
B15: 46033 | C15: =TEXT(B15,"ddd") -> Sun | D15: L | E15: L | F15: L | G15: =IF(F15="","",IF(F15<TIME(9,0,0),"LM",IF(F15="L","L","NO LM"))) -> L
B16: 46034 | C16: =TEXT(B16,"ddd") -> Mon | D16: 0.375 | E16: 0.75 | F16: =E16-D16 -> 0.375 | G16: =IF(F16="","",IF(F16<TIME(9,0,0),"LM",IF(F16="L","L","NO LM"))) -> NO LM
B17: 46035 | C17: =TEXT(B17,"ddd") -> Tue | D17: 0.4375 | E17: 0.75 | F17: =E17-D17 -> 0.3125 | G17: =IF(F17="","",IF(F17<TIME(9,0,0),"LM",IF(F17="L","L","NO LM"))) -> LM
B18: 46036 | C18: =TEXT(B18,"ddd") -> Wed | D18: 0.375 | E18: 0.75 | F18: =E18-D18 -> 0.375 | G18: =IF(F18="","",IF(F18<TIME(9,0,0),"LM",IF(F18="L","L","NO LM"))) -> NO LM
B19: 46037 | C19: =TEXT(B19,"ddd") -> Thu | D19: 0.375 | E19: 0.75 | F19: =E19-D19 -> 0.375 | G19: =IF(F19="","",IF(F19<TIME(9,0,0),"LM",IF(F19="L","L","NO LM"))) -> NO LM
B20: 46038 | C20: =TEXT(B20,"ddd") -> Fri | D20: 0.40625 | E20: 0.75 | F20: =E20-D20 -> 0.34375 | G20: =IF(F20="","",IF(F20<TIME(9,0,0),"LM",IF(F20="L","L","NO LM"))) -> LM
B21: 46039 | C21: =TEXT(B21,"ddd") -> Sat | D21: 0.375 | E21: 0.75 | F21: =E21-D21 -> 0.375 | G21: =IF(F21="","",IF(F21<TIME(9,0,0),"LM",IF(F21="L","L","NO LM"))) -> NO LM
B22: 46040 | C22: =TEXT(B22,"ddd") -> Sun | D22: L | E22: L | F22: L | G22: =IF(F22="","",IF(F22<TIME(9,0,0),"LM",IF(F22="L","L","NO LM"))) -> L
B23: 46041 | C23: =TEXT(B23,"ddd") -> Mon | D23: 0.375 | E23: 0.75 | F23: =E23-D23 -> 0.375 | G23: =IF(F23="","",IF(F23<TIME(9,0,0),"LM",IF(F23="L","L","NO LM"))) -> NO LM
B24: 46042 | C24: =TEXT(B24,"ddd") -> Tue | D24: 0.375 | E24: 0.75 | F24: =E24-D24 -> 0.375 | G24: =IF(F24="","",IF(F24<TIME(9,0,0),"LM",IF(F24="L","L","NO LM"))) -> NO LM
B25: 46043 | C25: =TEXT(B25,"ddd") -> Wed | D25: 0.43055556 | E25: 0.75 | F25: =E25-D25 -> 0.31944444 | G25: =IF(F25="","",IF(F25<TIME(9,0,0),"LM",IF(F25="L","L","NO LM"))) -> LM
B26: 46044 | C26: =TEXT(B26,"ddd") -> Thu | D26: 0.375 | E26: 0.75 | F26: =E26-D26 -> 0.375 | G26: =IF(F26="","",IF(F26<TIME(9,0,0),"LM",IF(F26="L","L","NO LM"))) -> NO LM
B27: 46045 | C27: =TEXT(B27,"ddd") -> Fri | D27: 0.375 | E27: 0.75 | F27: =E27-D27 -> 0.375 | G27: =IF(F27="","",IF(F27<TIME(9,0,0),"LM",IF(F27="L","L","NO LM"))) -> NO LM
B28: 46046 | C28: =TEXT(B28,"ddd") -> Sat | D28: 0.41666667 | E28: 0.75 | F28: =E28-D28 -> 0.33333333 | G28: =IF(F28="","",IF(F28<TIME(9,0,0),"LM",IF(F28="L","L","NO LM"))) -> LM
B29: 46047 | C29: =TEXT(B29,"ddd") -> Sun | D29: L | E29: L | F29: L | G29: =IF(F29="","",IF(F29<TIME(9,0,0),"LM",IF(F29="L","L","NO LM"))) -> L
B30: 46048 | C30: =TEXT(B30,"ddd") -> Mon | D30: 0.375 | E30: 0.75 | F30: =E30-D30 -> 0.375 | G30: =IF(F30="","",IF(F30<TIME(9,0,0),"LM",IF(F30="L","L","NO LM"))) -> NO LM
B31: 46049 | C31: =TEXT(B31,"ddd") -> Tue | D31: 0.375 | E31: 0.75 | F31: =E31-D31 -> 0.375 | G31: =IF(F31="","",IF(F31<TIME(9,0,0),"LM",IF(F31="L","L","NO LM"))) -> NO LM
B32: 46050 | C32: =TEXT(B32,"ddd") -> Wed | D32: 0.41666667 | E32: 0.75 | F32: =E32-D32 -> 0.33333333 | G32: =IF(F32="","",IF(F32<TIME(9,0,0),"LM",IF(F32="L","L","NO LM"))) -> LM
B33: 46051 | C33: =TEXT(B33,"ddd") -> Thu | D33: 0.375 | E33: 0.75 | F33: =E33-D33 -> 0.375 | G33: =IF(F33="","",IF(F33<TIME(9,0,0),"LM",IF(F33="L","L","NO LM"))) -> NO LM
B34: 46052 | C34: =TEXT(B34,"ddd") -> Fri | D34: 0.375 | E34: 0.75 | F34: =E34-D34 -> 0.375 | G34: =IF(F34="","",IF(F34<TIME(9,0,0),"LM",IF(F34="L","L","NO LM"))) -> NO LM
B35: 46053 | C35: =TEXT(B35,"ddd") -> Sat | D35: 0.37569444 | E35: 0.75 | F35: =E35-D35 -> 0.37430556 | G35: =IF(F35="","",IF(F35<TIME(9,0,0),"LM",IF(F35="L","L","NO LM"))) -> LM
